cvxpy_leximin/VERSION
cvxpy_leximin/__init__.py
cvxpy_leximin/objective.py
cvxpy_leximin/problem.py
cvxpy_leximin-0.5.dist-info/licenses/LICENSE
cvxpy_leximin-0.5.dist-info/METADATA
cvxpy_leximin-0.5.dist-info/WHEEL
cvxpy_leximin-0.5.dist-info/top_level.txt
cvxpy_leximin-0.5.dist-info/RECORD
