Metadata-Version: 2.4
Name: cvxpy_leximin
Version: 0.5
Summary: Let CVXPY support optimization in leximin order
Home-page: https://github.com/erelsgl/cvxpy_leximin
Author: Erel Segal-Halevi
Author-email: erelsgl@gmail.com
License: Apache License, Version 2.0
Project-URL: Bug Reports, https://github.com/erelsgl/cvxpy_leximin/issues
Project-URL: Source Code, https://github.com/erelsgl/cvxpy_leximin
Keywords: optimization,cvxpy,leximin
Classifier: Development Status :: 3 - Alpha
Requires-Python: >=3.8
License-File: LICENSE
Requires-Dist: cvxpy_base>=1.1
Dynamic: author
Dynamic: author-email
Dynamic: classifier
Dynamic: description
Dynamic: description-content-type
Dynamic: home-page
Dynamic: keywords
Dynamic: license
Dynamic: license-file
Dynamic: project-url
Dynamic: requires-dist
Dynamic: requires-python
Dynamic: summary
